utility_collection/__init__.py
utility_collection/__main__.py
utility_collection/build.py
utility_collection/common/__init__.py
utility_collection/common/download.py
utility_collection/download_file_samples/__init__.py
utility_collection/download_file_samples/__main__.py
utility_collection/download_file_samples/settings.py
utility_collection-0.1.1.dist-info/entry_points.txt
utility_collection-0.1.1.dist-info/LICENSE
utility_collection-0.1.1.dist-info/WHEEL
utility_collection-0.1.1.dist-info/METADATA
utility_collection-0.1.1.dist-info/RECORD
