Metadata-Version: 2.1
Name: utility-collection
Version: 0.1.1
Summary: 
License: MIT
Author: Qin Li
Author-email: liblaf@outlook.com
Requires-Python: >=3.10,<3.12
Classifier: License :: OSI Approved :: MIT License
Classifier: Programming Language :: Python :: 3
Classifier: Programming Language :: Python :: 3.10
Classifier: Programming Language :: Python :: 3.11
Requires-Dist: requests (>=2.28.1,<3.0.0)
Requires-Dist: rich (>=12.6.0,<13.0.0)
Requires-Dist: tqdm (>=4.64.1,<5.0.0)
